lightning_fastapi/__init__.py
lightning_fastapi/cli.py
lightning_fastapi/generator.py
lightning_fastapi-0.1.0.dist-info/LICENSE
lightning_fastapi-0.1.0.dist-info/METADATA
lightning_fastapi-0.1.0.dist-info/WHEEL
lightning_fastapi-0.1.0.dist-info/entry_points.txt
lightning_fastapi-0.1.0.dist-info/RECORD
