Metadata-Version: 2.3
Name: lightning-fastapi
Version: 0.1.0
Summary: Lightning FastAPI - A containerised quick starter template for FastAPI backends with pre-configured authentication, database connections, and Docker support.
License: MIT
Author: JY
Requires-Python: >=3.7
Classifier: Programming Language :: Python :: 3
Classifier: License :: OSI Approved :: MIT License
Classifier: Operating System :: OS Independent
Requires-Dist: inquirer (>=3.1.0)
Project-URL: Bug Tracker, https://github.com/yiyuan9/lightning-fastapi/issues
Project-URL: Homepage, https://github.com/yiyuan9/lightning-fastapi
